epicpath/EpicPath.py
epicpath/__init__.py
epic_path-0.1.1.dist-info/LICENSE
epic_path-0.1.1.dist-info/METADATA
epic_path-0.1.1.dist-info/WHEEL
epic_path-0.1.1.dist-info/top_level.txt
epic_path-0.1.1.dist-info/RECORD
