Metadata-Version: 2.1
Name: epic-path
Version: 0.1.1
Summary: A simple high level library to work with Path
Home-page: https://github.com/ValentinVignal/EpicPath.git
Author: Valentin Vignal
Author-email: valentin.vignal.dev@outlook.fr
License: MIT
Platform: UNKNOWN
